{
    "symbol": "DBC",
    "timestamp": "2025-08-20 10:43:15",
    "current_price": 29.25,
    "signal": "TRUNG LẬP",
    "recommendation": "GIỮ",
    "score": 46.5,
    "rsi_value": 45.29250832509398,
    "ma10": 30.4,
    "ma20": 30.166500000000003,
    "ma50": 29.208000000000002,
    "ma200": 25.38425,
    "rs": 0.017779533781114184,
    "rs_point": 22.635099272464693,
    "open": 29.3,
    "high": 29.9,
    "low": 29.05,
    "volume": 3209100.0,
    "macd": 0.20232318274273453,
    "macd_signal": 0.41771811861684327,
    "macd_hist": -0.21539493587410874,
    "bb_upper": 31.70591904626431,
    "bb_lower": 28.627080953735696,
    "volume_ma": null,
    "ichimoku_tenkan_sen": 30.700000000000003,
    "ichimoku_kijun_sen": 30.195,
    "ichimoku_senkou_span_a": 30.4475,
    "ichimoku_senkou_span_b": 28.96,
    "ichimoku_chikou_span": 29.22,
    "rs_sma_10": 0.018785580031676945,
    "rs_sma_20": 0.019202989283096064,
    "rs_sma_50": 0.019882562737335432,
    "rs_sma_200": 0.01918784492782557,
    "rs_point_sma_10": 26.265863772454697,
    "rs_point_sma_20": 26.25371598861829,
    "rs_point_sma_50": 19.80506723715369,
    "rs_point_sma_200": 7.27577096781451,
    "gemini_analysis": "Chào bạn,\n\nDựa trên dữ liệu kỹ thuật và tài chính bạn cung cấp cho mã DBC, tôi xin đưa ra phân tích chi tiết như sau:\n\n---\n\n**ĐÁNH GIÁ MÃ CHỨNG KHOÁN DBC**\n\n**1. Phân tích Kỹ thuật (Theo Wyckoff, VSA/VPA, Minervini, Alexander Elder)**\n\n*   **Hành động giá & Khối lượng (VSA/VPA, Wyckoff):**\n    *   Giá hiện tại (29.25) nằm dưới các đường MA ngắn hạn (MA10: 30.4, MA20: 30.16) và rất gần MA50 (29.20). Điều này cho thấy áp lực bán vẫn đang chi phối trong ngắn hạn và giá đang cố gắng tìm điểm cân bằng quanh MA50.\n    *   Điểm đáng chú ý là **khối lượng giao dịch hiện tại (3.2 triệu)** thấp hơn đáng kể so với khối lượng trung bình 20 ngày (12.17 triệu) và 50 ngày (11.42 triệu). Trong bối cảnh giá điều chỉnh hoặc đi ngang sau một xu hướng tăng, khối lượng thấp có thể là tín hiệu:\n        *   **Lack of Supply (Thiếu nguồn cung):** Áp lực bán đã giảm, nhưng chưa có lực cầu mạnh để đẩy giá lên.\n        *   **No Demand (Không có cầu):** Thiếu sự quan tâm từ phe mua, khiến giá khó phục hồi.\n        *   Đối với Wyckoff, khối lượng thấp khi giá giảm sau một giai đoạn tích lũy/phân phối có thể là một \"Test for Supply\" (kiểm tra nguồn cung). Tuy nhiên, nếu không có sự xuất hiện của khối lượng cầu lớn sau đó, giá có thể tiếp tục điều chỉnh hoặc đi ngang.\n*   **Cấu trúc xu hướng (Wyckoff, Minervini, Elder):**\n    *   **Dài hạn (Elder's First Screen):** Giá vẫn nằm trên MA200 (25.38), cho thấy xu hướng tăng dài hạn vẫn được duy trì.\n    *   **Trung hạn (Minervini, Elder's Second Screen):** Giá nằm dưới MA10 và MA20, nhưng vẫn giữ được trên MA50 (chỉ một chút). Đây là dấu hiệu của một xu hướng giảm hoặc tích lũy/đi ngang trong trung hạn. MACD cho tín hiệu cắt xuống (MACD < Signal, Histogram âm), xác nhận động lượng giảm.\n    *   **Ngắn hạn (Elder's Third Screen):** RSI ở mức 45.29, cho thấy DBC không quá mua hay quá bán, ở trạng thái trung lập. Bollinger Bands cho thấy giá gần biên dưới (28.62), có thể là vùng hỗ trợ, nhưng cần khối lượng xác nhận.\n    *   **Sức mạnh tương đối (Minervini):** Chỉ số RS (0.017) và RS_Point (22.6) cực kỳ thấp, cho thấy DBC đang hoạt động **rất kém hiệu quả** so với thị trường chung (VNINDEX). Điều này là một điểm trừ lớn theo tiêu chí của Minervini, người ưu tiên các cổ phiếu có sức mạnh tương đối vượt trội.\n*   **Mô hình kỹ thuật:** Chưa có mô hình kỹ thuật rõ ràng như VCP (Volatility Contraction Pattern) của Minervini hay các cấu trúc tích lũy/phân phối điển hình của Wyckoff được xác nhận. Giá đang trong giai đoạn điều chỉnh/tích lũy không rõ ràng.\n\n**2. Phân tích Cơ bản (Theo Warren Buffett, Charlie Munger, Peter Lynch, Seth Klarman)**\n\n*   **Tăng trưởng và Lợi nhuận:**\n    *   **Doanh thu:** DBC cho thấy sự tăng trưởng doanh thu ấn tượng trong dài hạn, đặc biệt là giai đoạn 2020-2021. Tuy nhiên, tốc độ tăng trưởng này rất **biến động qua từng quý/năm**, phản ánh tính chu kỳ cao của ngành nông nghiệp (biến động giá thịt lợn, thức ăn chăn nuôi).\n    *   **Lợi nhuận ròng:** Đây là điểm yếu lớn nhất của DBC. Lợi nhuận ròng có tính **chu kỳ cực cao và không ổn định**, với các quý thậm chí ghi nhận lỗ lớn (ví dụ: Q1/2023, Q4/2022). Điều này đi ngược lại hoàn toàn tiêu chí tìm kiếm các doanh nghiệp có lợi nhuận ổn định, tăng trưởng bền vững của Warren Buffett hay Peter Lynch (trừ khi là nhà đầu tư chuyên sâu vào cổ phiếu chu kỳ và có khả năng định thời điểm thị trường rất tốt).\n*   **Biên lợi nhuận (Gross Profit Margin - GPM):** GPM của DBC cũng biến động mạnh, từ mức cao trong năm 2020 (trên 20%) xuống rất thấp và thậm chí âm trong một số quý (Q1/2023). Mặc dù có dấu hiệu phục hồi trong các quý gần đây của 2024, sự không ổn định này cho thấy rủi ro cao từ biến động giá nguyên vật liệu đầu vào và giá bán sản phẩm đầu ra, ảnh hưởng trực tiếp đến khả năng sinh lời.\n*   **ROE (%):** ROE của DBC cũng rất thất thường và thường xuyên ở mức thấp hoặc âm khi công ty gặp khó khăn. Điều này cho thấy hiệu quả sử dụng vốn chủ sở hữu không ổn định, một yếu tố mà các nhà đầu tư giá trị như Buffett hay Lynch đặc biệt quan tâm để đánh giá lợi thế cạnh tranh của doanh nghiệp.\n*   **Nợ (Debt/Equity):** Tỷ lệ Nợ/Vốn chủ sở hữu của DBC duy trì tương đối ổn định quanh mức 1x. Với một doanh nghiệp sản xuất trong ngành nông nghiệp đòi hỏi vốn đầu tư lớn, mức nợ này có thể được xem là chấp nhận được, nhưng không phải là quá thấp theo tiêu chuẩn của nhà đầu tư thận trọng như Seth Klarman.\n*   **Dòng tiền (Cash Flow):** Dòng tiền hoạt động kinh doanh của DBC cũng **biến động rất mạnh**, có quý dương lớn nhưng cũng có quý âm sâu (Q1/2023 dòng tiền âm tới 872 tỷ). Khả năng tạo ra dòng tiền bền vững từ hoạt động cốt lõi là một tiêu chí quan trọng của các nhà đầu tư giá trị, và DBC đang cho thấy sự thiếu ổn định ở khía cạnh này.\n*   **Hàng tồn kho & Tài sản cố định:** Là một doanh nghiệp trong ngành nông nghiệp, DBC có lượng hàng tồn kho và tài sản cố định lớn, điều này là đặc thù ngành. Tuy nhiên, sự biến động lớn của hàng tồn kho (đặc biệt là giá trị) cũng góp phần vào tính chu kỳ của lợi nhuận.\n\n**3. Nhận định Xu hướng & Kết luận**\n\n*   **AI-derived Insights từ dữ liệu lịch sử giá:**\n    *   Lịch sử giá cho thấy DBC là một cổ phiếu có tính **biến động cao (high-beta)** và chịu ảnh hưởng mạnh bởi chu kỳ ngành (giá thịt lợn). Cổ phiếu đã trải qua những giai đoạn tăng trưởng nóng (2019-2020) và điều chỉnh sâu (2022).\n    *   Các chỉ báo cho thấy cổ phiếu đang trong giai đoạn **suy yếu về động lượng và sức mạnh tương đối** sau một nhịp hồi phục. Khối lượng khớp lệnh đang thấp hơn nhiều so với trung bình, cho thấy sự thiếu quyết đoán hoặc chờ đợi của dòng tiền lớn.\n*   **Xu hướng ngắn hạn (1-4 tuần):** Giá DBC có khả năng tiếp tục **đi ngang hoặc điều chỉnh nhẹ** quanh vùng MA50 (29.20) do thiếu lực cầu mạnh và động lượng giảm đang chi phối.\n*   **Xu hướng trung hạn (1-6 tháng):** Mặc dù xu hướng dài hạn vẫn là tăng (trên MA200), nhưng với sức mạnh tương đối kém và tình hình tài chính nhiều biến động, DBC có thể tiếp tục **underperform (kém hiệu quả hơn)** thị trường chung hoặc duy trì trong một vùng tích lũy/đi ngang rộng trước khi có một chu kỳ tăng giá mới rõ ràng.\n\n**4. Kết luận & Chấm điểm:**\n\nDBC là một cổ phiếu mang tính chu kỳ cao, với tiềm năng tăng trưởng mạnh mẽ trong các chu kỳ thuận lợi nhưng cũng tiềm ẩn rủi ro lớn trong các chu kỳ khó khăn. Các chỉ số cơ bản của DBC thể hiện sự thiếu ổn định về lợi nhuận và dòng tiền, điều này không phù hợp với các triết lý đầu tư giá trị bền vững. Về mặt kỹ thuật, cổ phiếu đang cho thấy sự suy yếu trong ngắn hạn và sức mạnh tương đối kém so với thị trường.\n\n*   **Kết luận cuối cùng:** **GIỮ** (Đối với nhà đầu tư đang nắm giữ và hiểu rõ tính chu kỳ của cổ phiếu, chấp nhận rủi ro và có tầm nhìn dài hạn hơn cho chu kỳ ngành tiếp theo). **BÁN** (Đối với nhà đầu tư đang nắm giữ với mục tiêu tăng trưởng và sức mạnh tương đối, hoặc nhà đầu tư mới có ý định mua vị thế hiện tại).\n\n*   **Chấm điểm mua vị thế giá hiện tại (1-10):** **3/10** (Thấp, do rủi ro tài chính biến động lớn, sức mạnh giá kém, và thiếu tín hiệu kỹ thuật xác nhận cho một xu hướng tăng rõ ràng)."
}