{
    "symbol": "DBC",
    "timestamp": "2025-08-18 10:54:52",
    "current_price": 29.9,
    "signal": "TRUNG LẬP",
    "recommendation": "GIỮ",
    "score": 51.75,
    "rsi_value": 49.768099745348245,
    "ma10": 30.520999999999997,
    "ma20": 30.235500000000002,
    "ma50": 29.0982,
    "ma200": 25.336399999999998,
    "rs": 0.01823059569538443,
    "rs_point": 23.698123367629506,
    "rs_point_252": 24.117891241178913,
    "open": 30.35,
    "high": 30.35,
    "low": 29.75,
    "volume": 4051700.0,
    "macd": 0.44927849369648243,
    "macd_signal": 0.5218409355328077,
    "macd_hist": -0.07256244183632532,
    "bb_upper": 31.668294123383173,
    "bb_lower": 28.80270587661683,
    "volume_ma": null,
    "ichimoku_tenkan_sen": 30.64111111111111,
    "ichimoku_kijun_sen": 30.011153846153846,
    "ichimoku_senkou_span_a": 30.326132478632477,
    "ichimoku_senkou_span_b": 26.202884615384615,
    "ichimoku_chikou_span": 29.31,
    "rs_sma_10": 0.019060638231901107,
    "rs_sma_20": 0.01940837440778923,
    "rs_sma_50": 0.01997711322952442,
    "rs_sma_200": 0.01920409863215521,
    "rs_point_sma_10": 27.050448387379685,
    "rs_point_sma_20": 26.380415727308883,
    "rs_point_sma_50": 19.094829565659776,
    "rs_point_sma_200": 7.281522040932454,
    "rs_point_252_sma_10": 28.996242992706357,
    "rs_point_252_sma_20": 27.817794880715137,
    "rs_point_252_sma_50": 15.675401029912436,
    "rs_point_252_sma_200": 17.489539926025046,
    "gemini_analysis": "Chào bạn, với vai trò là một chuyên gia phân tích chứng khoán Việt Nam, tôi xin đưa ra những đánh giá chi tiết về mã cổ phiếu DBC (Tập đoàn Dabaco Việt Nam) dựa trên các dữ liệu bạn cung cấp và thông tin tài chính công khai mới nhất.\n\n***Lưu ý quan trọng:*** *Dữ liệu tài chính bạn cung cấp trong bảng là của mã **DRI (Cao su Đắk Lắk)**, không phải của **DBC (Dabaco)**. Do đó, phần phân tích tài chính dưới đây sẽ dựa trên Báo cáo tài chính Quý 1/2024 đã được công bố của DBC để đảm bảo tính chính xác.*\n\n---\n\n### **ĐÁNH GIÁ TỔNG QUAN CỔ PHIẾU DBC**\n\n#### **1. Phân Tích Kỹ Thuật**\n\nDựa trên các chỉ số bạn cung cấp, đây là bức tranh kỹ thuật của DBC:\n\n*   **Xu hướng chính:**\n    *   Giá hiện tại (29.90) vẫn đang nằm trên các đường MA trung và dài hạn quan trọng là MA50 (29.10) và MA200 (25.34). Điều này khẳng định **xu hướng trung và dài hạn của DBC vẫn là TĂNG**.\n    *   Tuy nhiên, giá đang nằm dưới các đường MA ngắn hạn là MA10 (30.52) và MA20 (30.24), cho thấy cổ phiếu đang trong một **pha điều chỉnh hoặc tích lũy ngắn hạn**.\n\n*   **Các chỉ báo động lượng và biến động:**\n    *   **RSI (49.77):** Ở mức trung tính, không quá mua cũng không quá bán. Điều này cho thấy thị trường đang cân bằng và cổ phiếu có đủ không gian để tăng hoặc giảm.\n    *   **MACD (-0.07 Histogram):** Đường MACD đang có xu hướng cắt xuống đường Signal, và Histogram mang giá trị âm. Đây là một tín hiệu **yếu đi trong ngắn hạn**, cho thấy đà tăng đang chững lại và phe bán đang tạm chiếm ưu thế.\n    *   **Bollinger Bands:** Giá đang vận động ở nửa dưới của dải băng, gần đường MA20. Dải băng không quá thắt chặt hay mở rộng, cho thấy trạng thái đi ngang tích lũy là chủ đạo.\n    *   **Ichimoku:** Giá (29.90) đang nằm ngay dưới Kijun (30.01) và Tenkan (30.64) một chút, nhưng vẫn nằm trên đám mây Kumo. Đây là tín hiệu cho thấy một sự điều chỉnh nhẹ, nhưng xu hướng tăng vẫn được hỗ trợ bởi \"bệ đỡ\" là đám mây.\n\n*   **Phân tích Khối lượng (VPA/VSA):**\n    *   Khối lượng giao dịch phiên gần nhất (4.05 triệu cp) **thấp hơn rất nhiều** so với trung bình 20 ngày (12.7 triệu cp) và 50 ngày (11.3 triệu cp).\n    *   **Diễn giải:** Việc giá điều chỉnh nhẹ với khối lượng sụt giảm mạnh là một tín hiệu **TÍCH CỰC**. Nó cho thấy áp lực bán đã yếu đi đáng kể, lượng cung giá thấp không còn nhiều. Đây có thể là một pha \"kiểm tra cung\" (test for supply) trong một nền giá tích lũy.\n\n*   **Sức mạnh Tương đối (RS - theo Mark Minervini):**\n    *   Điểm RS_Point chỉ là 23.70, một con số khá thấp. Điều này cho thấy trong 1 năm qua, hiệu suất của DBC kém hơn so với phần lớn thị trường. Tuy nhiên, các chỉ số tài chính gần đây đang cho thấy sự thay đổi lớn, và giá thường đi sau câu chuyện cơ bản.\n\n**Tổng hợp PTKT:** DBC đang trong một xu hướng tăng trung hạn nhưng gặp phải một đợt điều chỉnh ngắn hạn lành mạnh. Tín hiệu đáng chú ý nhất là khối lượng cạn kiệt, cho thấy pha điều chỉnh có thể sắp kết thúc.\n\n---\n\n#### **2. Phân Tích Tình Hình Tài Chính (Dựa trên BCTC Quý 1/2024 của DBC)**\n\n*   **Kết quả kinh doanh đột phá:**\n    *   Quý 1/2024, DBC ghi nhận doanh thu thuần đạt **3,250 tỷ đồng**, tăng 40.7% so với cùng kỳ.\n    *   Quan trọng nhất, Lợi nhuận sau thuế đạt **72.6 tỷ đồng**, trong khi cùng kỳ năm trước lỗ nặng 321 tỷ đồng. Đây là một sự **thay đổi ngoạn mục**, chấm dứt chuỗi 5 quý thua lỗ liên tiếp.\n\n*   **Nguồn gốc Lợi nhuận và Lãi vay:**\n    *   **Lợi nhuận đến từ kinh doanh thuần:** Sự phục hồi lợi nhuận đến hoàn toàn từ mảng kinh doanh cốt lõi. Biên lợi nhuận gộp cải thiện mạnh mẽ từ -4.4% (Q1/2023) lên **12.1% (Q1/2024)**. Nguyên nhân chính là do **giá heo hơi phục hồi mạnh mẽ** trong khi giá nguyên liệu thức ăn chăn nuôi đầu vào đã hạ nhiệt.\n    *   **Chi phí lãi vay:** DBC vẫn là doanh nghiệp có tỷ lệ nợ vay cao. Chi phí lãi vay Q1/2024 là khoảng **100 tỷ đồng**. Tuy nhiên, với việc lợi nhuận từ hoạt động kinh doanh đã dương trở lại và đạt hơn 200 tỷ, công ty đã có đủ khả năng để trang trải chi phí này và vẫn có lãi. Khả năng thanh toán lãi vay đã được cải thiện đáng kể.\n\n*   **Triển vọng và Luận điểm đầu tư (Theo phong cách Warren Buffett):**\n    *   **Lợi thế cạnh tranh:** DBC là doanh nghiệp hàng đầu trong chuỗi giá trị 3F (Feed-Farm-Food). Việc tự chủ được nguồn giống, thức ăn giúp công ty có lợi thế về chi phí.\n    *   **\"Con hào kinh tế\" tiềm năng:** Câu chuyện lớn nhất của DBC trong trung và dài hạn là **Vaccine Dịch tả lợn Châu Phi (ASF)**. Nếu vaccine này được thương mại hóa thành công, nó sẽ mang lại nguồn doanh thu và lợi nhuận khổng lồ, thay đổi hoàn toàn vị thế của Dabaco. Đây chính là yếu tố tạo ra tiềm năng tăng trưởng đột biến.\n    *   **Rủi ro:** Rủi ro chính vẫn là tính chu kỳ của ngành chăn nuôi (giá heo hơi, dịch bệnh).\n\n---\n\n#### **3. Đánh Giá Theo Mô Hình & Nhận Định Xu Hướng**\n\n*   **Mô hình Wyckoff/VSA:** Cổ phiếu đã có một pha tăng giá mạnh (Mark Up). Giai đoạn hiện tại có thể được xem là một **vùng tái tích lũy (Re-accumulation)** hoặc một pha \"Backing Up\" sau khi bứt phá khỏi nền giá cũ. Việc giá điều chỉnh với khối lượng thấp (cạn cung) là đặc điểm kinh điển của giai đoạn này, chuẩn bị cho một đợt tăng giá tiếp theo.\n\n*   **Xu hướng ngắn hạn (1-4 tuần):** **Tích lũy đi ngang**. Giá có thể sẽ dao động trong biên độ **29.0 - 31.5**. Cần quan sát thêm tín hiệu dòng tiền quay trở lại.\n\n*   **Xu hướng trung hạn (3-6 tháng):** **TÍCH CỰC**. Xu hướng tăng giá chính vẫn được duy trì, được hỗ trợ bởi sự phục hồi của kết quả kinh doanh và kỳ vọng vào vaccine ASF.\n\n---\n\n#### **4. Kết Luận và Khuyến Nghị**\n\nKết hợp giữa phân tích kỹ thuật và cơ bản:\n- **Kỹ thuật:** Cổ phiếu đang trong một pha điều chỉnh lành mạnh, áp lực bán đã cạn kiệt.\n- **Cơ bản:** Doanh nghiệp đã chính thức thoát lỗ, lợi nhuận quay trở lại từ hoạt động cốt lõi và có câu chuyện tăng trưởng rất hấp dẫn phía trước.\n\n**KHUYẾN NGHỊ: MUA**\n\n**Chiến lược giải ngân:**\n*   **Vùng mua:** Có thể bắt đầu giải ngân từng phần quanh vùng hỗ trợ **29.0 - 29.5**. Mua gia tăng khi cổ phiếu có phiên bứt phá khỏi vùng 31.0 với khối lượng lớn, xác nhận kết thúc điều chỉnh.\n*   **Mục tiêu:**\n    *   Ngắn hạn: 32.0 (đỉnh cũ).\n    *   Trung hạn: 35.0 - 38.0.\n*   **Cắt lỗ:** Khi giá đóng cửa dưới vùng **28.0** (thủng nền hỗ trợ gần nhất)."
}