{
    "symbol": "DBC",
    "timestamp": "2025-08-19 14:35:08",
    "current_price": 29.35,
    "signal": "TĂNG MẠNH",
    "recommendation": "GIỮ - TĂNG",
    "score": 64.0,
    "rsi_value": 45.98323485945303,
    "ma10": 30.467000000000002,
    "ma20": 30.208499999999997,
    "ma50": 29.158,
    "ma200": 25.3587,
    "rs": 0.017822659978867852,
    "rs_point": 22.89065339233233,
    "rs_point_252": 24.7874149659864,
    "open": 29.5,
    "high": 29.85,
    "low": 29.2,
    "volume": 10568300.0,
    "macd": 0.30317707350217304,
    "macd_signal": 0.4723645733830917,
    "macd_hist": -0.16918749988091863,
    "bb_upper": 31.685365261288695,
    "bb_lower": 28.7316347387113,
    "volume_ma": null,
    "ichimoku_tenkan_sen": 30.533333333333335,
    "ichimoku_kijun_sen": 29.982307692307696,
    "ichimoku_senkou_span_a": 30.257820512820516,
    "ichimoku_senkou_span_b": 26.31826923076923,
    "ichimoku_chikou_span": 29.65,
    "rs_sma_10": 0.018916706249477725,
    "rs_sma_20": 0.019312703736615908,
    "rs_sma_50": 0.019935197370683364,
    "rs_sma_200": 0.019195197403797427,
    "rs_point_sma_10": 26.60778079801828,
    "rs_point_sma_20": 26.36034657423803,
    "rs_point_sma_50": 19.477086749003234,
    "rs_point_sma_200": 7.279415578475817,
    "rs_point_252_sma_10": 28.09230869877721,
    "rs_point_252_sma_20": 28.044988234332976,
    "rs_point_252_sma_50": 16.165692201361413,
    "rs_point_252_sma_200": 17.35490342674257,
    "gemini_analysis": "Chắc chắn rồi, với vai trò là một chuyên gia phân tích chứng khoán, tôi sẽ đưa ra đánh giá chi tiết về mã cổ phiếu DBC của Tập đoàn Dabaco Việt Nam.\n\n**TỔNG QUAN VỀ DBC (TẬP ĐOÀN DABACO VIỆT NAM)**\n\nDBC là một doanh nghiệp hàng đầu trong ngành nông nghiệp Việt Nam, hoạt động theo mô hình chuỗi giá trị 3F (Feed - Farm - Food). Đây là một cổ phiếu mang tính chu kỳ cao, phụ thuộc lớn vào giá nguyên liệu đầu vào (ngô, đậu tương) và giá bán sản phẩm đầu ra (chủ yếu là giá heo hơi).\n\n---\n\n### **1. PHÂN TÍCH KỸ THUẬT (Wyckoff, VSA/VPA, Minervini)**\n\n**Hành động Giá & Khối lượng (VSA/VPA):**\n\n*   **Hành động giá gần đây:** Cổ phiếu đang trong một đợt điều chỉnh ngắn hạn sau khi đạt đỉnh quanh vùng 31.x. Giá hiện tại (29.35) đã giảm xuống dưới các đường MA ngắn hạn (MA10, MA20), cho thấy áp lực bán trong ngắn hạn.\n*   **Phân tích khối lượng:** Phiên giao dịch gần nhất có khối lượng (10.5 triệu cp) thấp hơn mức trung bình 20 ngày (12.9 triệu cp) và 50 ngày (11.5 triệu cp). Việc giá giảm với khối lượng thấp là một tín hiệu tương đối tích cực, cho thấy áp lực bán không mạnh, chủ yếu là hoạt động chốt lời hoặc rũ bỏ của nhà đầu tư nhỏ lẻ. Đây không phải là một phiên phân phối mạnh (Distribution).\n\n**Cấu trúc Xu hướng & Giai đoạn (Wyckoff/Minervini):**\n\n*   **Giai đoạn xu hướng (Minervini):** DBC đang ở trong **Giai đoạn 2 (Stage 2 - Tăng giá)**.\n    *   Giá nằm trên đường MA200 (25.35) và MA200 đang dốc lên.\n    *   Giá cũng nằm trên MA50 (29.15).\n    *   Tuy nhiên, giá hiện đang nằm dưới MA10 và MA20, cho thấy cổ phiếu đang trong một đợt điều chỉnh/củng cố tự nhiên trong một xu hướng tăng.\n*   **Phân tích Wyckoff:** Sau một giai đoạn tăng giá mạnh (Mark Up), DBC đang bước vào một vùng Tái tích lũy (Re-accumulation) hoặc Phân phối (Distribution). Dựa trên việc giá giảm với khối lượng thấp, khả năng cao đây là một **vùng Tái tích lũy** để chuẩn bị cho nhịp tăng tiếp theo. Vùng hỗ trợ quan trọng là MA50 (quanh 29.15) và dải dưới của Bollinger Bands (28.7). Một pha kiểm tra (test) lại vùng hỗ trợ này với khối lượng cạn kiệt sẽ là tín hiệu tốt.\n\n**Các chỉ báo chính:**\n\n*   **RSI (45.98):** Ở mức trung tính, cho thấy động lượng tăng đã suy yếu nhưng chưa đi vào vùng quá bán.\n*   **MACD:** Đã cắt xuống đường tín hiệu và histogram đang âm, xác nhận cho xu hướng điều chỉnh ngắn hạn.\n*   **Sức mạnh tương đối (RS):** Các chỉ số RS so với VNINDEX đều đang có xu hướng giảm trong ngắn hạn, cho thấy DBC đang yếu hơn thị trường chung trong vài tuần gần đây. Đây là một điểm trừ theo tiêu chí của Minervini.\n\n**Mô hình Kỹ thuật:**\n\n*   Cổ phiếu đang có dấu hiệu hình thành một nền giá phẳng sau nhịp tăng mạnh. Vùng giá 28.5 - 31.5 đang là vùng giằng co. Nếu giữ được trên vùng hỗ trợ 28.5, đây có thể là một nền giá tốt để bứt phá lên các vùng cao hơn.\n\n---\n\n### **2. PHÂN TÍCH CƠ BẢN (Buffett, Lynch, Klarman)**\n\n**Tổng quan Tăng trưởng & Lợi nhuận (Peter Lynch):**\n\n*   DBC là một cổ phiếu **chu kỳ điển hình**. Sau 2 năm khó khăn (2022-2023) với lợi nhuận sụt giảm mạnh, thậm chí thua lỗ, công ty đang cho thấy dấu hiệu của một pha **\"Lột xác\" (Turnaround)** mạnh mẽ trong năm 2024.\n*   **Doanh thu & Lợi nhuận:** Báo cáo tài chính cho thấy sự cải thiện vượt bậc. Q1/2024 ghi nhận doanh thu tăng 39% và lợi nhuận ròng 72.6 tỷ đồng, so với mức lỗ -320 tỷ của cùng kỳ năm trước. Đây là tín hiệu đảo chiều rất quan trọng, chủ yếu đến từ việc giá heo hơi phục hồi mạnh mẽ trong khi giá nguyên liệu thức ăn chăn nuôi đã hạ nhiệt.\n*   **Biên lợi nhuận:** Biên lợi nhuận gộp đã cải thiện rõ rệt từ mức rất thấp trong năm 2023 lên trên 10% trong Q1/2024 và dự kiến tiếp tục cải thiện, đây là động lực chính cho sự phục hồi lợi nhuận.\n\n**Sức khỏe Tài chính (Buffett, Klarman):**\n\n*   **Nợ vay:** Tỷ lệ Nợ/Vốn chủ sở hữu (D/E) ở mức cao (khoảng 1.7 lần tại Q2/2024), phần lớn là nợ vay ngắn hạn. Đây là một rủi ro cần lưu ý, đặc trưng của ngành cần vốn lưu động lớn. Warren Buffett sẽ không ưa thích một doanh nghiệp có đòn bẩy cao và biên lợi nhuận thiếu ổn định như vậy.\n*   **Khả năng thanh toán:** Tỷ lệ thanh toán hiện hành (Current Ratio) chỉ ở mức ~1.0, cho thấy khả năng thanh toán các khoản nợ ngắn hạn không quá dồi dào.\n*   **Hàng tồn kho & Tài sản cố định:** Hàng tồn kho rất lớn (5.8 nghìn tỷ) và là một phần cốt lõi của hoạt động kinh doanh. Rủi ro về dịch bệnh và biến động giá có thể ảnh hưởng lớn đến giá trị hàng tồn kho. Tài sản cố định lớn cho thấy quy mô sản xuất và đầu tư bài bản theo mô hình 3F.\n\n**Dòng tiền:**\n\n*   Dòng tiền từ hoạt động kinh doanh (CFO) đã dương trở lại trong Q1/2024 sau 2 năm âm liên tiếp. Đây là một dấu hiệu cực kỳ quan trọng, cho thấy doanh nghiệp đã bắt đầu tạo ra tiền mặt từ hoạt động cốt lõi, củng cố cho câu chuyện phục hồi.\n\n---\n\n### **3. NHẬN ĐỊNH XU HƯỚNG**\n\n*   **Ngắn hạn (1–4 tuần):** **Trung lập - Tích lũy.** Cổ phiếu có thể tiếp tục đi ngang hoặc điều chỉnh nhẹ về vùng hỗ trợ **28.7 - 29.2**. Áp lực bán đã suy yếu và cổ phiếu đang cần thời gian để hấp thụ lượng cung chốt lời.\n*   **Trung hạn (1–6 tháng):** **Tích cực.** Câu chuyện phục hồi kết quả kinh doanh dựa trên chu kỳ giá heo hơi được dự báo sẽ tiếp tục là động lực chính. Nếu kết quả kinh doanh Q2 và Q3/2024 tiếp tục khả quan, DBC có khả năng sẽ vượt đỉnh cũ và hướng tới các mục tiêu cao hơn.\n\n---\n\n### **4. KẾT LUẬN VÀ KHUYẾN NGHỊ**\n\n*   **Tóm tắt:** DBC là một cổ phiếu chu kỳ đang trong giai đoạn phục hồi mạnh mẽ về cơ bản. Về kỹ thuật, cổ phiếu đang trong một xu hướng tăng trung hạn và đang có một đợt điều chỉnh lành mạnh. Rủi ro chính đến từ cơ cấu nợ vay cao và tính biến động của ngành.\n*   **Khuyến nghị:** **MUA**\n    *   **Chiến lược:** Có thể bắt đầu mua thăm dò ở vùng giá hiện tại và gia tăng tỷ trọng nếu giá kiểm tra thành công vùng hỗ trợ 28.7 - 29.2 với khối lượng thấp, hoặc khi giá bứt phá trở lại trên đường MA20 (vùng 30.2) với khối lượng lớn.\n*   **Chấm điểm (vị thế mua tại giá 29.35):** **7/10**\n    *   (Điểm 7 cho tiềm năng phục hồi lớn, nhưng trừ 3 điểm cho rủi ro về đòn bẩy tài chính cao và tính chu kỳ khó lường của ngành)."
}