{
    "symbol": "PXL",
    "timestamp": "2025-08-19 14:00:17",
    "current_price": 20.8,
    "signal": "MUA MẠNH",
    "recommendation": "MUA MẠNH",
    "score": 100.0,
    "rsi_value": 79.75262197294157,
    "ma10": 18.45,
    "ma20": 17.94,
    "ma50": 14.958,
    "ma200": 13.703499999999998,
    "rs": 0.012587294094864625,
    "rs_point": 58.43968825660757,
    "rs_point_252": 63.77952755905514,
    "open": 20.0,
    "high": 21.0,
    "low": 19.5,
    "volume": 1376500.0,
    "macd": 1.2537804969767024,
    "macd_signal": 1.1392165924106512,
    "macd_hist": 0.11456390456605114,
    "bb_upper": 19.851439248315437,
    "bb_lower": 16.028560751684566,
    "volume_ma": null,
    "ichimoku_tenkan_sen": 18.555555555555557,
    "ichimoku_kijun_sen": 17.126923076923077,
    "ichimoku_senkou_span_a": 17.841239316239317,
    "ichimoku_senkou_span_b": 12.586538461538462,
    "ichimoku_chikou_span": 13.4,
    "rs_sma_10": 0.011444038963102237,
    "rs_sma_20": 0.011456585118251133,
    "rs_sma_50": 0.010144485705363367,
    "rs_sma_200": 0.010371091039411704,
    "rs_point_sma_10": 42.71832974729679,
    "rs_point_sma_20": 39.822281660542046,
    "rs_point_sma_50": 13.026761670845131,
    "rs_point_sma_200": 6.255625406182832,
    "rs_point_252_sma_10": 44.065256490482035,
    "rs_point_252_sma_20": 35.98707818691152,
    "rs_point_252_sma_50": 6.875995754272023,
    "rs_point_252_sma_200": 21.799682002219345,
    "gemini_analysis": "Chắc chắn rồi, với vai trò là một chuyên gia phân tích chứng khoán Việt Nam, tôi sẽ đưa ra đánh giá chi tiết về mã cổ phiếu PXL (Công ty Cổ phần Đầu tư Khu Công nghiệp Dầu khí Long Sơn) dựa trên các dữ liệu bạn cung cấp.\n\n---\n\n### **BÁO CÁO PHÂN TÍCH CỔ PHIẾU PXL (Ngày 19/08/2025)**\n\n**Giá hiện tại: 20,800 VND**\n\n#### **I. PHÂN TÍCH KỸ THUẬT**\n\n**1. Hành động Giá & Khối lượng (Wyckoff, VSA/VPA, Minervini):**\n*   **Hành động giá:** Cổ phiếu đang trong một pha **Tăng tốc (Mark Up)** cực kỳ mạnh mẽ. Phiên giao dịch gần nhất (19/08/2025) là một cây nến tăng giá mạnh mẽ (Marubozu hoặc gần Marubozu) với giá đóng cửa ở mức cao nhất, thể hiện sức mạnh áp đảo của bên mua.\n*   **Khối lượng (VSA/VPA):** Khối lượng giao dịch (1.37 triệu cp) cao hơn mức trung bình 20 ngày (1.2 triệu cp) và cao hơn đáng kể so với trung bình 50 ngày (607k cp). Đây là tín hiệu **\"Nỗ lực đẩy giá thành công\" (Effort to Rise)**, cho thấy dòng tiền lớn đang tích cực tham gia và xác nhận cho xu hướng tăng giá.\n*   **Cấu trúc xu hướng (Minervini):** PXL đang thể hiện đầy đủ các đặc điểm của một siêu cổ phiếu ở **Giai đoạn 2 (Stage 2 Uptrend)**:\n    *   Giá nằm trên các đường MA 50, 150 (dữ liệu không có nhưng có thể suy ra), và 200.\n    *   MA 200 đang dốc lên.\n    *   Các đường MA ngắn hạn (10, 20, 50) nằm trên các đường MA dài hạn hơn theo thứ tự.\n    *   Giá hiện tại cao hơn nhiều so với đáy 52 tuần.\n\n**2. Đánh giá các chỉ báo (Elder):**\n*   **Xu hướng (MA, Ichimoku):** Tất cả các đường MA đều cho thấy xu hướng tăng mạnh. Giá nằm trên Mây Kumo và Tenkan > Kijun, xác nhận xu hướng tăng giá mạnh mẽ trên cả khung ngắn và trung hạn.\n*   **Sức mạnh (RSI, MACD):**\n    *   **RSI (79.75):** Đã đi vào vùng **quá mua (overbought)**. Theo Alexander Elder, đây là tín hiệu cho thấy phe mua đang \"hưng phấn tột độ\" và tiềm ẩn rủi ro điều chỉnh ngắn hạn. Cần thận trọng với các vị thế mua đuổi.\n    *   **MACD:** Đường MACD nằm trên đường Signal và Histogram dương, ủng hộ đà tăng giá tiếp diễn.\n*   **Đột biến (Bollinger Bands):** Giá đã vượt ra ngoài dải Bollinger trên (20.8 > 19.85), cho thấy một sự bứt phá mạnh mẽ nhưng cũng hàm ý giá đang bị kéo dãn quá mức so với mức trung bình và có thể sớm điều chỉnh trở lại vào trong dải.\n\n**3. Sức mạnh tương đối (RS - Minervini):**\n*   Các chỉ số RS (RS so với VNINDEX, RS_Point) đều nằm trên các đường SMA của chính nó, cho thấy PXL đang **mạnh hơn thị trường chung** một cách rõ rệt. Đây là một tiêu chí quan trọng của các cổ phiếu dẫn dắt.\n\n**4. Mô hình kỹ thuật & Nhận định từ Lịch sử giá:**\n*   **Mô hình:** Cổ phiếu đã hoàn thành một **mô hình nền giá phẳng (Flat Base)** kéo dài nhiều năm ở vùng giá rất thấp (dưới 10.0). Cú bứt phá gần đây là điểm phá vỡ (breakout) khỏi nền giá này, kích hoạt một chu kỳ tăng giá mới.\n*   **Phân tích Lịch sử giá (AI-driven Insight):** Dữ liệu lịch sử từ 2015 cho thấy PXL có đặc tính của một cổ phiếu mang tính đầu cơ cao, thường xuyên có những giai đoạn đi ngang kéo dài với thanh khoản thấp, sau đó là những đợt sóng tăng giá đột biến, dựng đứng với khối lượng bùng nổ (như cuối 2021, đầu 2019). Đợt tăng giá hiện tại là mạnh nhất trong lịch sử, cho thấy kỳ vọng của thị trường vào \"câu chuyện\" của doanh nghiệp đang rất lớn.\n\n---\n\n#### **II. PHÂN TÍCH CƠ BẢN**\n\n**1. Tổng quan (Warren Buffett, Charlie Munger):**\n*   PXL có một lịch sử kinh doanh cực kỳ yếu kém. Báo cáo tài chính qua các năm cho thấy một bức tranh ảm đạm:\n    *   **Lợi nhuận:** Liên tục báo lỗ hoặc lợi nhuận không đáng kể trong suốt một thập kỷ. **ROE hầu hết là số âm**, cho thấy công ty không tạo ra giá trị cho cổ đông mà ngược lại, đang bào mòn vốn.\n    *   **Dòng tiền:** Dòng tiền từ hoạt động kinh doanh (CFO) đa số các năm đều âm nặng. Đây là một **cảnh báo đỏ rực**, cho thấy doanh nghiệp không thể tự tạo ra tiền mặt từ hoạt động cốt lõi để duy trì và phát triển.\n    *   **Biên lợi nhuận:** Gần như không có, thậm chí biên lợi nhuận gộp nhiều quý/năm là số âm. Doanh nghiệp không có lợi thế cạnh tranh bền vững (con hào kinh tế).\n\n**2. Sức khỏe tài chính (Seth Klarman):**\n*   **Nợ:** Tỷ lệ Nợ/Vốn chủ sở hữu không quá cao, nhưng đó là do vốn chủ sở hữu đã bị bào mòn qua nhiều năm thua lỗ. Công ty dường như hoạt động dựa nhiều vào các khoản phải trả và chiếm dụng vốn.\n*   **Tài sản:**\n    *   **Hàng tồn kho và Phải thu dài hạn:** Chiếm tỷ trọng cực lớn trong tổng tài sản. Đây chính là \"câu chuyện\" của PXL - giá trị tài sản nằm ở các dự án bất động sản KCN (chủ yếu là dự án KCN Dầu khí Long Sơn). Tuy nhiên, các tài sản này đã tồn tại trên BCTC trong nhiều năm mà không tạo ra doanh thu/lợi nhuận tương xứng, đặt ra câu hỏi lớn về tính khả thi và tiến độ của dự án.\n    *   **Tiền mặt:** Lượng tiền và tương đương tiền rất mỏng so với quy mô tổng tài sản, cho thấy rủi ro thanh khoản cao.\n\n**3. Góc nhìn Peter Lynch:**\n*   PXL là một cổ phiếu thuộc dạng **\"Tài sản ẩn\" (Asset Play)** hoặc **\"Turnaround\" (Tái cấu trúc)**. Giá cổ phiếu tăng không phải vì kết quả kinh doanh quá khứ hay hiện tại, mà vì thị trường đang \"định giá lại\" giá trị của quỹ đất mà PXL sở hữu, đặc biệt khi có những thông tin tích cực về việc triển khai dự án KCN Long Sơn. Việc đầu tư vào PXL là đặt cược vào tương lai của dự án này.\n\n---\n\n#### **III. NHẬN ĐỊNH VÀ KHUYẾN NGHỊ**\n\n**1. Nhận định xu hướng:**\n*   **Ngắn hạn (1–4 tuần):** Xu hướng tăng rất mạnh. Tuy nhiên, cổ phiếu đang ở trạng thái **quá mua cực độ**. Rủi ro điều chỉnh/tích lũy lại là rất cao. Các nhịp rung lắc mạnh có thể xảy ra. Vùng hỗ trợ gần nhất là MA10 quanh 18.5 và xa hơn là vùng đỉnh cũ 16.0-17.0.\n*   **Trung hạn (1–6 tháng):** Xu hướng tăng đã được xác lập. Chừng nào cổ phiếu còn duy trì trên MA50 (hiện tại là 15.0), xu hướng tăng trung hạn vẫn được bảo toàn. Động lực tăng giá sẽ phụ thuộc vào dòng tiền đầu cơ và các thông tin liên quan đến tiến độ dự án KCN Long Sơn.\n\n**2. Tổng kết:**\nPXL là một trường hợp kinh điển của sự đối nghịch giữa Phân tích Kỹ thuật và Phân tích Cơ bản:\n*   **Kỹ thuật:** Xuất sắc. Một trong những cổ phiếu có sức mạnh giá và dòng tiền tốt nhất thị trường hiện tại.\n*   **Cơ bản:** Cực kỳ yếu kém. Lịch sử kinh doanh thua lỗ, dòng tiền âm, không có lợi thế cạnh tranh.\n\nSự tăng giá của PXL hoàn toàn dựa trên **kỳ vọng** vào câu chuyện tái cấu trúc và giá trị quỹ đất. Đây là một cổ phiếu mang tính **đầu cơ cao**, không dành cho nhà đầu tư giá trị hoặc những người không chấp nhận rủi ro lớn.\n\n#### **3. Kết luận cuối cùng:**\n\n*   **Đối với nhà đầu tư đang nắm giữ:** **GIỮ**\n    *   Tiếp tục nắm giữ và nâng điểm chặn lãi (trailing stop-loss) lên vùng 18.0. Nếu giá vi phạm mốc này, nên chốt lời một phần hoặc toàn bộ.\n*   **Đối với nhà đầu tư muốn mua mới:** **QUAN SÁT, CHƯA MUA ĐUỔI**\n    *   Rủi ro khi mua ở giá hiện tại là rất cao do cổ phiếu đã tăng tốc và ở trạng thái quá mua. Chờ đợi một nhịp điều chỉnh lành mạnh về vùng hỗ trợ **17.0 - 18.5** với khối lượng thấp để xem xét mở vị thế.\n\n**ĐIỂM SỐ CỔ PHIẾU: 4/10**\n*(Điểm số thấp do rủi ro cực lớn từ nền tảng cơ bản yếu kém, mặc dù tín hiệu kỹ thuật rất mạnh)*"
}